{
    "posts": [
        {
            "name": "Anonymous webscraping",
            "slug": "anonymous_webscraping_post",
            "technology": "Python",
            "main_photo_path": "img/posts/anonymous_webscraping/main.jpg"
        },
        {
            "name": "Maps with R",
            "slug": "maps_with_r_post",
            "technology": "R",
            "main_photo_path": "img/posts/maps_with_r/main.png"
        },
        {
            "name": "Mallorca geocoder",
            "slug": "mallorca_geocoder_post",
            "technology": "Java",
            "main_photo_path": "img/posts/mallorca_geocoder/main.jpeg"
        },
        {
            "name": "Spanish text mining",
            "slug": "spanish_text_mining_post",
            "technology": "Python",
            "main_photo_path": "img/posts/spanish_text_mining/main.png"
        },
        {
            "name": "Multitenant architecture",
            "slug": "multitenant_architecture_post",
            "technology": "Django and Postgres",
            "main_photo_path": "img/posts/multitenant_architecture/main.png"
        },
        {
            "name": "Tensorflow, Spark & Cassandra",
            "slug": "tensorsparkandra_post",
            "technology": "Scala",
            "main_photo_path": "img/posts/tensorsparkandra/main.jpg"
        },
        {
            "name": "Distributed matrix product",
            "slug": "distributed_matrix_product_post",
            "technology": "CUDA",
            "main_photo_path": "img/posts/distributed_matrix_product/main.jpg"
        },
        {
            "name": "Automatic differentiation",
            "slug": "automatic_differentiation_post",
            "technology": "Tensorflow & Autograd",
            "main_photo_path": "img/posts/automatic_differentiation/main.png"
        },
        {
            "name": "Variational inference I",
            "slug": "variational_inference_1_post",
            "technology": "Statistics",
            "main_photo_path": "img/posts/variational_inference/main1.png"
        },
        {
            "name": "Variational inference II",
            "slug": "variational_inference_2_post",
            "technology": "Statistics",
            "main_photo_path": "img/posts/variational_inference/main2.png"
        },
        {
            "name": "Variational inference III",
            "slug": "variational_inference_3_post",
            "technology": "Statistics",
            "main_photo_path": "img/posts/variational_inference/main3.png"
        },
        {
            "name": "Profiling on social networks",
            "slug": "profiling_on_social_networks_post",
            "technology": "Topic modeling with Python",
            "main_photo_path": "img/posts/profiling_on_social_networks/main.png"
        }
    ]
}
